razer/__init__.py
razer/razer.py
razer/razer_nt.py
mouse_movement-0.1.dist-info/METADATA
mouse_movement-0.1.dist-info/WHEEL
mouse_movement-0.1.dist-info/top_level.txt
mouse_movement-0.1.dist-info/RECORD
