Metadata-Version: 2.2
Name: mouse-movement
Version: 0.1
Summary: A library for controlling mouse and keyboard via ctypes on Windows
Home-page: https://github.com/yourusername/mouse-movement
Author: Your Name
Author-email: your.email@example.com
Classifier: Programming Language :: Python :: 3
Classifier: License :: OSI Approved :: MIT License
Classifier: Operating System :: Microsoft :: Windows
Dynamic: author
Dynamic: author-email
Dynamic: classifier
Dynamic: description
Dynamic: description-content-type
Dynamic: home-page
Dynamic: summary
